setup.py
dsnd_probability654321/Binomialdistribution.py
dsnd_probability654321/Gaussiandistribution.py
dsnd_probability654321/Generaldistribution.py
dsnd_probability654321/__init__.py
dsnd_probability654321.egg-info/PKG-INFO
dsnd_probability654321.egg-info/SOURCES.txt
dsnd_probability654321.egg-info/dependency_links.txt
dsnd_probability654321.egg-info/not-zip-safe
dsnd_probability654321.egg-info/top_level.txt